LICENSE.txt
MANIFEST.in
README.rst
pavement.py
requirements.txt
setup.py
docs/api.rst
docs/conf.py
docs/generated_build_test.csv
docs/index.rst
docs/log/generated_buildlog_min_1.txt
docs/log/generated_buildlog_min_2.txt
docs/log/generated_buildlog_min_3.txt
docs/log/generated_buildlog_min_4.txt
docs/log/generated_buildlog_min_5.txt
docs/log/generated_buildlog_min_6.txt
docs/log/generated_buildlog_min_7.txt
pyavrutils/SConstruct
pyavrutils/__init__.py
pyavrutils/about.py
pyavrutils/arduino.py
pyavrutils/avrgcc.py
pyavrutils/avrsize.py
pyavrutils/support.py
pyavrutils/util.py
pyavrutils.egg-info/PKG-INFO
pyavrutils.egg-info/SOURCES.txt
pyavrutils.egg-info/dependency_links.txt
pyavrutils.egg-info/requires.txt
pyavrutils.egg-info/top_level.txt
pyavrutils/cli/__init__.py
pyavrutils/cli/arduino/__init__.py
pyavrutils/cli/arduino/build.py
pyavrutils/examples/__init__.py
pyavrutils/examples/deadcode.py
pyavrutils/examples/delaysize.py
pyavrutils/examples/minsize.py
pyavrutils/examples/minsize_arduino.py
pyavrutils/examples/pgmspace.py
pyavrutils/examples/simple.py
pyavrutils/examples/targets.py
pyavrutils/examples/usage_ard.py
pyavrutils/examples/usage_avr.py