Metadata-Version: 1.1
Name: pyavrutils
Version: 0.3
Summary: pyavrutils is a Python library that can build AVR_ and arduino_ code at runtime.
Home-page: https://github.com/ponty/pyavrutils
Author: ponty
Author-email: UNKNOWN
License: BSD
Keywords: avr
Platform: UNKNOWN
Classifier: License :: OSI Approved :: BSD License
Classifier: Natural Language :: English
Classifier: Operating System :: OS Independent
Classifier: Programming Language :: Python
Classifier: Programming Language :: Python :: 2
Classifier: Programming Language :: Python :: 2.7
Classifier: Programming Language :: Python :: 3
Classifier: Programming Language :: Python :: 3.3
Classifier: Programming Language :: Python :: 3.4
Classifier: Programming Language :: Python :: 3.5
